{"config":{"output_file":null,"full_docs":false,"pub_only":false,"reachable_only":false,"distro_crate":false,"signatures":false,"borrow_data":false},"version":"0.19.0","compilation":{"directory":"/Users/jhonnatha/Projects/rust/minigrep","program":"/Users/jhonnatha/.rustup/toolchains/stable-x86_64-apple-darwin/bin/rls","arguments":[],"output":"/Users/jhonnatha/Projects/rust/minigrep/target/rls/debug/deps/libminigrep-d7170634cf6e6835.rmeta"},"prelude":{"crate_id":{"name":"minigrep","disambiguator":[13450776911660185210,12924924996350375778]},"crate_root":"src","external_crates":[{"file_name":"/Users/jhonnatha/Projects/rust/minigrep/src/main.rs","num":1,"id":{"name":"std","disambiguator":[9176452395873514981,10525323411957323785]}},{"file_name":"/Users/jhonnatha/Projects/rust/minigrep/src/main.rs","num":2,"id":{"name":"core","disambiguator":[15010738070622620763,9605760616786660431]}},{"file_name":"/Users/jhonnatha/Projects/rust/minigrep/src/main.rs","num":3,"id":{"name":"compiler_builtins","disambiguator":[8211843569075862794,5370502913999467694]}},{"file_name":"/Users/jhonnatha/Projects/rust/minigrep/src/main.rs","num":4,"id":{"name":"rustc_std_workspace_core","disambiguator":[5168977417888994485,12129851499920233632]}},{"file_name":"/Users/jhonnatha/Projects/rust/minigrep/src/main.rs","num":5,"id":{"name":"alloc","disambiguator":[9254821246596336482,1562696929571001984]}},{"file_name":"/Users/jhonnatha/Projects/rust/minigrep/src/main.rs","num":6,"id":{"name":"libc","disambiguator":[4867494102928472883,16549916413327868340]}},{"file_name":"/Users/jhonnatha/Projects/rust/minigrep/src/main.rs","num":7,"id":{"name":"unwind","disambiguator":[12208796569805280475,9421298070223625802]}},{"file_name":"/Users/jhonnatha/Projects/rust/minigrep/src/main.rs","num":8,"id":{"name":"cfg_if","disambiguator":[16776259526442764164,2692171601035033462]}},{"file_name":"/Users/jhonnatha/Projects/rust/minigrep/src/main.rs","num":9,"id":{"name":"hashbrown","disambiguator":[8506315589905780113,7752550639658555424]}},{"file_name":"/Users/jhonnatha/Projects/rust/minigrep/src/main.rs","num":10,"id":{"name":"rustc_std_workspace_alloc","disambiguator":[6004073670142137807,10055010459345902388]}},{"file_name":"/Users/jhonnatha/Projects/rust/minigrep/src/main.rs","num":11,"id":{"name":"rustc_demangle","disambiguator":[13812981793209371227,10465105188798852626]}},{"file_name":"/Users/jhonnatha/Projects/rust/minigrep/src/main.rs","num":12,"id":{"name":"addr2line","disambiguator":[12279896640040761358,16819944754252654372]}},{"file_name":"/Users/jhonnatha/Projects/rust/minigrep/src/main.rs","num":13,"id":{"name":"gimli","disambiguator":[502125910674001101,4874613814734389117]}},{"file_name":"/Users/jhonnatha/Projects/rust/minigrep/src/main.rs","num":14,"id":{"name":"object","disambiguator":[6964077277237141888,7151316435171244180]}},{"file_name":"/Users/jhonnatha/Projects/rust/minigrep/src/main.rs","num":15,"id":{"name":"panic_unwind","disambiguator":[5505266058476155326,9550778519957076375]}},{"file_name":"/Users/jhonnatha/Projects/rust/minigrep/src/main.rs","num":16,"id":{"name":"minigrep","disambiguator":[10300060142106568147,13819857492419654714]}}],"span":{"file_name":"src/main.rs","byte_start":0,"byte_end":291,"line_start":1,"line_end":16,"column_start":1,"column_end":2}},"imports":[{"kind":"Use","ref_id":{"krate":1,"index":1550},"span":{"file_name":"src/main.rs","byte_start":9,"byte_end":12,"line_start":1,"line_end":1,"column_start":10,"column_end":13},"alias_span":null,"name":"env","value":"","parent":{"krate":0,"index":0}},{"kind":"Use","ref_id":{"krate":2,"index":20},"span":{"file_name":"src/main.rs","byte_start":9,"byte_end":12,"line_start":1,"line_end":1,"column_start":10,"column_end":13},"alias_span":null,"name":"env","value":"","parent":{"krate":0,"index":3}},{"kind":"Use","ref_id":{"krate":1,"index":4305},"span":{"file_name":"src/main.rs","byte_start":23,"byte_end":30,"line_start":2,"line_end":2,"column_start":10,"column_end":17},"alias_span":null,"name":"process","value":"","parent":{"krate":0,"index":0}},{"kind":"Use","ref_id":{"krate":16,"index":5},"span":{"file_name":"src/main.rs","byte_start":47,"byte_end":53,"line_start":4,"line_end":4,"column_start":15,"column_end":21},"alias_span":null,"name":"Config","value":"","parent":{"krate":0,"index":0}}],"defs":[{"kind":"Mod","id":{"krate":0,"index":0},"span":{"file_name":"src/main.rs","byte_start":0,"byte_end":291,"line_start":1,"line_end":16,"column_start":1,"column_end":2},"name":"","qualname":"::","value":"src/main.rs","parent":null,"children":[{"krate":0,"index":1},{"krate":0,"index":2},{"krate":0,"index":3},{"krate":0,"index":8},{"krate":0,"index":4},{"krate":0,"index":5},{"krate":0,"index":6}],"decl_id":null,"docs":"","sig":null,"attributes":[]},{"kind":"Function","id":{"krate":0,"index":6},"span":{"file_name":"src/main.rs","byte_start":59,"byte_end":63,"line_start":6,"line_end":6,"column_start":4,"column_end":8},"name":"main","qualname":"::main","value":"fn main()","parent":null,"children":[],"decl_id":null,"docs":"","sig":null,"attributes":[]},{"kind":"Local","id":{"krate":0,"index":2147483654},"span":{"file_name":"src/main.rs","byte_start":76,"byte_end":80,"line_start":7,"line_end":7,"column_start":9,"column_end":13},"name":"args","qualname":"args$HirId { owner: DefId(0:6 ~ minigrep[baaa]::main[0]), local_id: 1 }","value":"std::vec::Vec<std::string::String>","parent":null,"children":[],"decl_id":null,"docs":"","sig":null,"attributes":[]},{"kind":"Local","id":{"krate":0,"index":1073741830},"span":{"file_name":"src/main.rs","byte_start":128,"byte_end":134,"line_start":9,"line_end":9,"column_start":9,"column_end":15},"name":"config","qualname":"config$HirId { owner: DefId(0:6 ~ minigrep[baaa]::main[0]), local_id: 2 }","value":"minigrep::Config","parent":null,"children":[],"decl_id":null,"docs":"","sig":null,"attributes":[]},{"kind":"Local","id":{"krate":0,"index":3221225478},"span":{"file_name":"src/main.rs","byte_start":172,"byte_end":175,"line_start":9,"line_end":9,"column_start":53,"column_end":56},"name":"err","qualname":"$HirId { owner: DefId(0:6 ~ minigrep[baaa]::main[0]), local_id: 37 }::err","value":"&str","parent":null,"children":[],"decl_id":null,"docs":"","sig":null,"attributes":[]},{"kind":"Local","id":{"krate":0,"index":2684354566},"span":{"file_name":"src/main.rs","byte_start":229,"byte_end":230,"line_start":13,"line_end":13,"column_start":16,"column_end":17},"name":"e","qualname":"e$HirId { owner: DefId(0:6 ~ minigrep[baaa]::main[0]), local_id: 5 }","value":"std::boxed::Box<dyn std::error::Error>","parent":null,"children":[],"decl_id":null,"docs":"","sig":null,"attributes":[]}],"impls":[],"refs":[{"kind":"Mod","span":{"file_name":"src/main.rs","byte_start":4,"byte_end":7,"line_start":1,"line_end":1,"column_start":5,"column_end":8},"ref_id":{"krate":1,"index":0}},{"kind":"Mod","span":{"file_name":"src/main.rs","byte_start":18,"byte_end":21,"line_start":2,"line_end":2,"column_start":5,"column_end":8},"ref_id":{"krate":1,"index":0}},{"kind":"Mod","span":{"file_name":"src/main.rs","byte_start":37,"byte_end":45,"line_start":4,"line_end":4,"column_start":5,"column_end":13},"ref_id":{"krate":16,"index":0}},{"kind":"Type","span":{"file_name":"src/main.rs","byte_start":82,"byte_end":85,"line_start":7,"line_end":7,"column_start":15,"column_end":18},"ref_id":{"krate":5,"index":4366}},{"kind":"Type","span":{"file_name":"src/main.rs","byte_start":86,"byte_end":92,"line_start":7,"line_end":7,"column_start":19,"column_end":25},"ref_id":{"krate":5,"index":5079}},{"kind":"Function","span":{"file_name":"src/main.rs","byte_start":108,"byte_end":115,"line_start":7,"line_end":7,"column_start":41,"column_end":48},"ref_id":{"krate":2,"index":5094}},{"kind":"Function","span":{"file_name":"src/main.rs","byte_start":101,"byte_end":105,"line_start":7,"line_end":7,"column_start":34,"column_end":38},"ref_id":{"krate":1,"index":1631}},{"kind":"Mod","span":{"file_name":"src/main.rs","byte_start":96,"byte_end":99,"line_start":7,"line_end":7,"column_start":29,"column_end":32},"ref_id":{"krate":1,"index":1550}},{"kind":"Function","span":{"file_name":"src/main.rs","byte_start":156,"byte_end":170,"line_start":9,"line_end":9,"column_start":37,"column_end":51},"ref_id":{"krate":2,"index":5810}},{"kind":"Function","span":{"file_name":"src/main.rs","byte_start":145,"byte_end":148,"line_start":9,"line_end":9,"column_start":26,"column_end":29},"ref_id":{"krate":16,"index":9}},{"kind":"Type","span":{"file_name":"src/main.rs","byte_start":137,"byte_end":143,"line_start":9,"line_end":9,"column_start":18,"column_end":24},"ref_id":{"krate":16,"index":5}},{"kind":"Variable","span":{"file_name":"src/main.rs","byte_start":150,"byte_end":154,"line_start":9,"line_end":9,"column_start":31,"column_end":35},"ref_id":{"krate":0,"index":2147483654}},{"kind":"Function","span":{"file_name":"src/main.rs","byte_start":196,"byte_end":200,"line_start":10,"line_end":10,"column_start":18,"column_end":22},"ref_id":{"krate":1,"index":4462}},{"kind":"Mod","span":{"file_name":"src/main.rs","byte_start":187,"byte_end":194,"line_start":10,"line_end":10,"column_start":9,"column_end":16},"ref_id":{"krate":1,"index":4305}},{"kind":"Function","span":{"file_name":"src/main.rs","byte_start":244,"byte_end":247,"line_start":13,"line_end":13,"column_start":31,"column_end":34},"ref_id":{"krate":16,"index":10}},{"kind":"Mod","span":{"file_name":"src/main.rs","byte_start":234,"byte_end":242,"line_start":13,"line_end":13,"column_start":21,"column_end":29},"ref_id":{"krate":16,"index":0}},{"kind":"Variable","span":{"file_name":"src/main.rs","byte_start":248,"byte_end":254,"line_start":13,"line_end":13,"column_start":35,"column_end":41},"ref_id":{"krate":0,"index":1073741830}},{"kind":"Type","span":{"file_name":"src/main.rs","byte_start":225,"byte_end":228,"line_start":13,"line_end":13,"column_start":12,"column_end":15},"ref_id":{"krate":2,"index":30410}},{"kind":"Type","span":{"file_name":"src/main.rs","byte_start":225,"byte_end":228,"line_start":13,"line_end":13,"column_start":12,"column_end":15},"ref_id":{"krate":2,"index":30410}},{"kind":"Function","span":{"file_name":"src/main.rs","byte_start":275,"byte_end":279,"line_start":14,"line_end":14,"column_start":18,"column_end":22},"ref_id":{"krate":1,"index":4462}},{"kind":"Mod","span":{"file_name":"src/main.rs","byte_start":266,"byte_end":273,"line_start":14,"line_end":14,"column_start":9,"column_end":16},"ref_id":{"krate":1,"index":4305}}],"macro_refs":[],"relations":[]}